dvc_stage/__init__.py
dvc_stage/cli.py
dvc_stage/config.py
dvc_stage/loading.py
dvc_stage/transforming.py
dvc_stage/utils.py
dvc_stage/validating.py
dvc_stage/writing.py
dvc_stage-1.1.0.dist-info/licenses/COPYING
dvc_stage-1.1.0.dist-info/METADATA
dvc_stage-1.1.0.dist-info/WHEEL
dvc_stage-1.1.0.dist-info/entry_points.txt
dvc_stage-1.1.0.dist-info/top_level.txt
dvc_stage-1.1.0.dist-info/RECORD
