Metadata-Version: 2.4
Name: dvc-stage
Version: 1.1.0
License: GPLv3
Project-URL: Changelog, https://github.com/MArpogaus/dvc-stage/blob/dev/CHANGELOG.md
Project-URL: Documentation, https://marpogaus.github.io/dvc-stage
Project-URL: Issues, https://github.com/MArpogaus/dvc-stage/issues
Project-URL: Repository, https://github.com/MArpogaus/dvc-stage
Classifier: Programming Language :: Python :: 3.8
Classifier: Programming Language :: Python :: 3.9
Classifier: Programming Language :: Python :: 3.10
Classifier: Programming Language :: Python :: 3.11
Requires-Python: >=3.9
License-File: COPYING
Requires-Dist: dvc>=2.12
Requires-Dist: pandas>=0.20
Requires-Dist: pyyaml>=5
Provides-Extra: develop
Requires-Dist: commitizen; extra == "develop"
Requires-Dist: ipykernel; extra == "develop"
Requires-Dist: pre-commit; extra == "develop"
Requires-Dist: pylsp-rope; extra == "develop"
Requires-Dist: python-lsp-ruff; extra == "develop"
Requires-Dist: python-lsp-server[all]; extra == "develop"
Requires-Dist: ruff; extra == "develop"
Provides-Extra: docs
Requires-Dist: pdoc; extra == "docs"
Provides-Extra: test
Requires-Dist: pytest; extra == "test"
Requires-Dist: pytest-xdist; extra == "test"
Dynamic: license-file
